pigeon/__init__.py
pigeon/shortcuts.py
pigeon/conf/__init__.py
pigeon/conf/manager.py
pigeon/conf/middleware.py
pigeon/conf/settings.py
pigeon/core/__init__.py
pigeon/core/app.py
pigeon/core/handler.py
pigeon/core/secure.py
pigeon/core/server.py
pigeon/default/__init__.py
pigeon/default/errors.py
pigeon/files/__init__.py
pigeon/files/media.py
pigeon/files/static.py
pigeon/http/__init__.py
pigeon/http/common.py
pigeon/http/message.py
pigeon/http/request.py
pigeon/http/response.py
pigeon/middleware/__init__.py
pigeon/middleware/auth.py
pigeon/middleware/pipe.py
pigeon/middleware/processing.py
pigeon/middleware/views.py
pigeon/middleware/components/__init__.py
pigeon/middleware/components/cache_control.py
pigeon/middleware/components/component.py
pigeon/middleware/components/connection.py
pigeon/middleware/components/content_negotiation.py
pigeon/middleware/components/cookies.py
pigeon/middleware/components/cors.py
pigeon/middleware/components/date.py
pigeon/middleware/components/host.py
pigeon/middleware/components/mediafiles.py
pigeon/middleware/components/method.py
pigeon/middleware/components/server.py
pigeon/middleware/components/staticfiles.py
pigeon/middleware/conversion/__init__.py
pigeon/middleware/conversion/converter.py
pigeon/middleware/conversion/mime/__init__.py
pigeon/middleware/conversion/mime/generators.py
pigeon/middleware/conversion/mime/parsers.py
pigeon/templating/__init__.py
pigeon/templating/templater.py
pigeon/utils/__init__.py
pigeon/utils/common.py
pigeon/utils/logger.py
pigeonpost-0.4.9.dist-info/METADATA
pigeonpost-0.4.9.dist-info/WHEEL
pigeonpost-0.4.9.dist-info/entry_points.txt
pigeonpost-0.4.9.dist-info/top_level.txt
pigeonpost-0.4.9.dist-info/RECORD
