Metadata-Version: 2.1
Name: pigeonpost
Version: 0.4.9
Summary: Simple to use Web Framework
License: MIT
Requires-Python: >=3.11
Requires-Dist: jinja2
Requires-Dist: rich
Requires-Dist: watchdog
